lc/__init__.py
lc/data.json
lc/lc.py
lc/template.md
leetcode_with_me-0.2.2.dist-info/LICENSE
leetcode_with_me-0.2.2.dist-info/METADATA
leetcode_with_me-0.2.2.dist-info/WHEEL
leetcode_with_me-0.2.2.dist-info/entry_points.txt
leetcode_with_me-0.2.2.dist-info/top_level.txt
leetcode_with_me-0.2.2.dist-info/RECORD
