Metadata-Version: 2.1
Name: leetcode-with-me
Version: 0.2.2
Summary: LeetCode CLI interface and helper functions.
Home-page: https://github.com/weiranfu/leetcode-with-me
Author: Weiran Fu
License: MIT
Platform: UNKNOWN
Classifier: Topic :: Utilities
Classifier: License :: OSI Approved :: MIT License
Classifier: Environment :: Console
Classifier: Intended Audience :: Developers
Classifier: Operating System :: OS Independent
Classifier: Programming Language :: Python :: 3 :: Only
Requires-Python: >= 3.6
Requires-Dist: markdown (>=3.0)
